LICENSE
README
README.md
pyproject.toml
pypatch_url/__init__.py
pypatch_url/command.py
pypatch_url/patch.py
pypatch_url.egg-info/PKG-INFO
pypatch_url.egg-info/SOURCES.txt
pypatch_url.egg-info/dependency_links.txt
pypatch_url.egg-info/entry_points.txt
pypatch_url.egg-info/requires.txt
pypatch_url.egg-info/top_level.txt
tests/test_basic.py
tests/test_cli.py
tests/test_helpers.py
tests/test_integration.py
tests/test_path_stripping.py
tests/test_url_support.py